life_stream_cli/__init__.py
life_stream_cli/__main__.py
life_stream_cli/client.py
life_stream_cli/config.py
life_stream_cli/subcommands/__init__.py
life_stream_cli/subcommands/config/__init__.py
life_stream_cli/subcommands/config/config_utils.py
life_stream_cli/subcommands/config/credentials_utils.py
life_stream_cli-0.2.7.dist-info/entry_points.txt
life_stream_cli-0.2.7.dist-info/WHEEL
life_stream_cli-0.2.7.dist-info/METADATA
life_stream_cli-0.2.7.dist-info/RECORD
